GOCPT/__init__.py
GOCPT/datasets.py
GOCPT/gotc.py
GOCPT/gotf.py
GOCPT/metrics.py
GOCPT/otc.py
GOCPT/otf.py
GOCPT/simulation.py
GOCPT/utils.py
GOCPT-0.1.1.dist-info/LICENSE
GOCPT-0.1.1.dist-info/METADATA
GOCPT-0.1.1.dist-info/WHEEL
GOCPT-0.1.1.dist-info/entry_points.txt
GOCPT-0.1.1.dist-info/top_level.txt
GOCPT-0.1.1.dist-info/RECORD
