Metadata-Version: 2.1
Name: GOCPT
Version: 0.1.1
Summary: A package for generalized online tensor decomposition and completion
Home-page: https://github.com/ycq091044/GOCPT
Author: Chaoqi Yang
Author-email: chaoqiy2@illinois.edu
License: UNKNOWN
Platform: UNKNOWN
Classifier: Programming Language :: Python :: 3
Classifier: License :: OSI Approved :: MIT License
Classifier: Operating System :: OS Independent
Requires-Dist: numpy (>=1.14.4)
